example_roxy/__init__.py
example_roxy/model/__init__.py
example_roxy-0.0.1.dist-info/LICENSE
example_roxy-0.0.1.dist-info/METADATA
example_roxy-0.0.1.dist-info/WHEEL
example_roxy-0.0.1.dist-info/top_level.txt
example_roxy-0.0.1.dist-info/RECORD
