Metadata-Version: 2.1
Name: example-roxy
Version: 0.0.1
Summary: No description.
Home-page: 
Author: roxy
Author-email: xxx@qq.com
Classifier: Programming Language :: Python :: 3
Classifier: License :: OSI Approved :: MIT License
Classifier: Operating System :: OS Independent
Requires-Python: >=3.7
License-File: LICENSE
